libcove2/__init__.py
libcove2/common.py
libcove2-0.2.1.dist-info/LICENSE.rst
libcove2-0.2.1.dist-info/METADATA
libcove2-0.2.1.dist-info/WHEEL
libcove2-0.2.1.dist-info/top_level.txt
libcove2-0.2.1.dist-info/RECORD
