Metadata-Version: 2.1
Name: libcove2
Version: 0.2.1
Summary: A data review library
Home-page: https://github.com/OpenDataServices/lib-cove-2
Author: Open Data Services
Author-email: code@opendataservices.coop
Requires-Python: >=3.8
License-File: LICENSE.rst
Requires-Dist: requests
Provides-Extra: dev
Requires-Dist: pytest; extra == "dev"
Requires-Dist: black; extra == "dev"
Requires-Dist: isort; extra == "dev"
Requires-Dist: flake8; extra == "dev"
Requires-Dist: mypy; extra == "dev"
Requires-Dist: sphinx; extra == "dev"
Requires-Dist: odsc-default-sphinx-theme; extra == "dev"
